getIOU/__init__.py
getIOU/get_iou.py
getIOU-0.0.1.dist-info/LICENSE
getIOU-0.0.1.dist-info/METADATA
getIOU-0.0.1.dist-info/WHEEL
getIOU-0.0.1.dist-info/top_level.txt
getIOU-0.0.1.dist-info/RECORD
