Metadata-Version: 2.1
Name: getIOU
Version: 0.0.1
Summary: This package computes the IOU between boxes for a variety of different bounding box formats.
Home-page: https://github.com/jafekb/getIOU
Author: Ben Jafek
Author-email: jafek91@gmail.com
License: UNKNOWN
Platform: UNKNOWN
Classifier: Programming Language :: Python :: 3
Classifier: License :: OSI Approved :: MIT License
Classifier: Operating System :: OS Independent
